langchain_undatasio/__init__.py
langchain_undatasio/document_loaders.py
langchain_undatasio-1.0.1.dist-info/METADATA
langchain_undatasio-1.0.1.dist-info/WHEEL
langchain_undatasio-1.0.1.dist-info/licenses/LICENSE
langchain_undatasio-1.0.1.dist-info/RECORD
